odoo/addons/sale_coupon_mass_mailing/README.rst
odoo/addons/sale_coupon_mass_mailing/__init__.py
odoo/addons/sale_coupon_mass_mailing/__manifest__.py
odoo/addons/sale_coupon_mass_mailing/i18n/es.po
odoo/addons/sale_coupon_mass_mailing/i18n/sale_coupon_mass_mailing.pot
odoo/addons/sale_coupon_mass_mailing/models/__init__.py
odoo/addons/sale_coupon_mass_mailing/models/mailing_mailing.py
odoo/addons/sale_coupon_mass_mailing/models/sale_coupon_program.py
odoo/addons/sale_coupon_mass_mailing/readme/CONTRIBUTORS.rst
odoo/addons/sale_coupon_mass_mailing/readme/DESCRIPTION.rst
odoo/addons/sale_coupon_mass_mailing/static/description/icon.png
odoo/addons/sale_coupon_mass_mailing/static/description/index.html
odoo/addons/sale_coupon_mass_mailing/tests/__init__.py
odoo/addons/sale_coupon_mass_mailing/tests/test_sale_coupon.py
odoo/addons/sale_coupon_mass_mailing/views/mailing_mailing_view.xml
odoo/addons/sale_coupon_mass_mailing/views/sale_coupon_program_view.xml
odoo13_addon_sale_coupon_mass_mailing-13.0.1.1.0.dist-info/METADATA
odoo13_addon_sale_coupon_mass_mailing-13.0.1.1.0.dist-info/WHEEL
odoo13_addon_sale_coupon_mass_mailing-13.0.1.1.0.dist-info/top_level.txt
odoo13_addon_sale_coupon_mass_mailing-13.0.1.1.0.dist-info/RECORD
